slurm/__init__.py
slurm/constants.py
slurm/files.py
slurm/modules.py
slurm/network.py
slurm/rate.py
slurm/scistorage.py
slurm/sig.py
slurm/simple_process.py
slurm/storage.py
slurm-0.5.1.dist-info/LICENSE
slurm-0.5.1.dist-info/WHEEL
slurm-0.5.1.dist-info/METADATA
slurm-0.5.1.dist-info/RECORD
