Metadata-Version: 2.1
Name: slurm
Version: 0.5.1
Summary: A bunch tools I have created over the years
Home-page: https://pypi.org/project/slurm/
License: MIT
Keywords: fun
Author: walchko
Author-email: walchko@users.noreply.github.com
Requires-Python: >=3.8
Classifier: Development Status :: 4 - Beta
Classifier: Intended Audience :: Developers
Classifier: License :: OSI Approved :: MIT License
Classifier: Operating System :: OS Independent
Classifier: Programming Language :: Python :: 3
Classifier: Programming Language :: Python :: 3.10
Classifier: Programming Language :: Python :: 3.8
Classifier: Programming Language :: Python :: 3.9
Classifier: Topic :: Software Development :: Libraries
Classifier: Topic :: Software Development :: Libraries :: Application Frameworks
Classifier: Topic :: Software Development :: Libraries :: Python Modules
Requires-Dist: pyyaml
Project-URL: Repository, https://github.com/MomsFriendlyRobotCompany/slurm
